PQMusic/OpenSans.ttf
PQMusic/PQMusic.pro
PQMusic/__init__.py
PQMusic/__init__.py.bck
PQMusic/icon.svg
PQMusic/images.qrc
PQMusic/images_rc.py
PQMusic/no_cover.svg
PQMusic/player.py
PQMusic/player.py.bck
PQMusic/style.qss
PQMusic/utils.py
PQMusic/locales/es.qm
PQMusic/ui/Ui_add_url_dialog.py
PQMusic/ui/Ui_gui.py
PQMusic/ui/images_rc.py
PQMusic/ui/open_url_dialog.py
pqmusic-1.0.0.1.data/scripts/pqmusic
pqmusic-1.0.0.1.dist-info/LICENSE
pqmusic-1.0.0.1.dist-info/METADATA
pqmusic-1.0.0.1.dist-info/WHEEL
pqmusic-1.0.0.1.dist-info/top_level.txt
pqmusic-1.0.0.1.dist-info/RECORD
