Metadata-Version: 2.1
Name: pqmusic
Version: 1.0.0.1
Summary: A minimal music player.
Home-page: https://github.com/son-link/PQMusic
Author: Alfonso Saavedra 'Son Link'
Author-email: sonlink.dourden@gmail.com
License: GPL 3.0
Download-URL: https://github.com/son-link/PQMusic/archive/refs/tags/v.0.3.0.tar.gz
Keywords: music,audio,player
Platform: UNKNOWN
Classifier: Development Status :: 5 - Production/Stable
Classifier: Environment :: X11 Applications :: Qt
Classifier: Topic :: Multimedia :: Sound/Audio
Classifier: Topic :: Multimedia :: Sound/Audio :: Players
Classifier: License :: OSI Approved :: GNU General Public License v3 or later (GPLv3+)
Classifier: Programming Language :: Python :: 3
Classifier: Programming Language :: Python :: 3.4
Classifier: Programming Language :: Python :: 3.5
Classifier: Programming Language :: Python :: 3.6
Classifier: Programming Language :: Python :: 3.7
Classifier: Programming Language :: Python :: 3.8
Classifier: Programming Language :: Python :: 3.9
Classifier: Intended Audience :: End Users/Desktop
Classifier: Operating System :: OS Independent
License-File: LICENSE
Requires-Dist: pyqt5
Requires-Dist: mutagen
Requires-Dist: python-magic
Requires-Dist: requests
